Workbook

Sheet README
A1: Atlas Finance v3 database
A3: Назначение | B3: База для Google Sheets и будущего веб-приложения
A4: Главный источник фактов | B4: Transactions
A5: Текущие операции сохранены | B5: 26
A6: Фактический остаток cashflow | B6: 1 580 ₽ на ВТБ до 15-го
A7: Инвестиционный фонд | B7: 153 000 ₽, не входит в дневной лимит
A8: Выплаты | B8: зарплата 15-го 185 000 ₽, аванс 30-го 15 000 ₽
A9: UX-идея | B9: MonthlyReview хранит вопросы месяца: родителям, ЖКХ, инвестиции, цели
A10: Импорт в Google Sheets | B10: Загрузить этот xlsx как Google Sheets, потом подключить Apps Script API
A11: Правило | B11: Не редактировать id вручную после подключения приложения
A12: Версия | B12: v3 draft, 2026-06-12

Sheet Settings
A1: key | B1: value | C1: type | D1: notes
A2: currency | B2: RUB | C2: string | D2: Основная валюта
A3: as_of_date | B3: 46185 | C3: date | D3: Дата сборки базы
A4: salary_day | B4: 15 | C4: number | D4: День основной зарплаты
A5: advance_day | B5: 30 | C5: number | D5: День аванса
A6: salary_amount | B6: 185000 | C6: money | D6: Плановая зарплата
A7: advance_amount | B7: 15000 | C7: money | D7: Плановый аванс
A8: payday_move_rule | B8: previous-business-day | C8: string | D8: Если выходной, перенос на предыдущий рабочий день
A9: current_cycle_start | B9: 46171 | C9: date | D9: Старт текущего цикла
A10: current_cycle_end | B10: 46188 | C10: date | D10: Следующее поступление
A11: timezone | B11: Europe/Moscow | C11: string | D11: Часовой пояс пользователя

Sheet Accounts
A1: account_id | B1: name | C1: account_type | D1: current_balance | E1: include_in_cashflow | F1: include_in_net_worth | G1: currency | H1: as_of_date | I1: notes
A2: vtb_main | B2: ВТБ | C2: checking | D2: 1417 | E2: TRUE | F2: TRUE | G2: RUB | H2: 46185.345 | I2: Фактический остаток до 15-го числа
A3: brokerage | B3: Фонд в акциях/облигациях | C3: investment | D3: 153000 | E3: FALSE | F3: TRUE | G3: RUB | H3: 46185 | I3: Не учитывать в дневном лимите, но держать для net worth
A4: cash | B4: Наличные | C4: cash | D4: 0 | E4: TRUE | F4: TRUE | G4: RUB | H4: 46185 | I4: Запасная строка

Sheet IncomeSchedule
A1: income_id | B1: name | C1: day_of_month | D1: amount | E1: move_rule | F1: default_account_id | G1: active | H1: notes
A2: salary | B2: Зарплата | C2: 15 | D2: 185000 | E2: previous-business-day | F2: vtb_main | G2: TRUE | H2: Основная зарплата
A3: advance | B3: Аванс | C3: 30 | D3: 15000 | E3: previous-business-day | F3: vtb_main | G3: TRUE | H3: Аванс

Sheet BudgetGroups
A1: budget_group_id | B1: name | C1: group_type | D1: monthly_limit | E1: include_in_daily_limit | F1: notes
A2: food_home | B2: Еда дома | C2: variable | D2: 25000 | E2: TRUE | F2: из текущего Ref
A3: food_out | B3: Еда вне дома и досуг | C3: variable | D3: 10000 | E3: TRUE | F3: разделено на рабочую еду и бар/досуг
A4: transport_fuel_tolls | B4: Бензин и платные дороги | C4: transport | D4: 20000 | E4: TRUE | F4: из текущего Ref
A5: car_service | B5: Текущие расходы авто | C5: variable | D5: 10000 | E5: TRUE | F5: добавлено из текущей фактической структуры
A6: communications | B6: Связь/подписки | C6: fixed | D6: 10000 | E6: TRUE | F6: из текущего Ref
A7: shopping_hobby | B7: Одежда/техника/хобби/подарки | C7: variable | D7: 10000 | E7: TRUE | F7: из текущего Ref
A8: people_transfers | B8: Переводы людям | C8: variable | D8: 5000 | E8: TRUE | F8: стартовый лимит из текущего приложения
A9: health | B9: Здоровье | C9: variable | D9: 20000 | E9: TRUE | F9: из текущего Ref
A10: cat | B10: Кошка | C10: variable | D10: 5000 | E10: TRUE | F10: из текущего Ref
A11: family_support | B11: Родителям | C11: obligation | D11: 30000 | E11: FALSE | F11: baseline, каждый месяц подтверждать руками
A12: housing | B12: ЖКХ/дом/парковка | C12: obligation | D12: 10000 | E12: FALSE | F12: baseline, каждый месяц подтверждать руками
A13: goals | B13: Накопления | C13: saving | D13: 40000 | E13: FALSE | F13: НЗ, часы, машина, подушка, отпуск
... A16: other | B16: Прочее | C16: other | D16: 0 | E16: TRUE | F16: только для временной классификации

Sheet Categories
A1: category_id | B1: name | C1: budget_group_id | D1: record_type | E1: purpose | F1: active | G1: notes
A2: food_groceries | B2: Еда дома | C2: food_home | D2: expense | E2: Продукты для дома | F2: TRUE | G2: Супермаркеты, продукты домой
A3: food_workday | B3: Еда вне дома: завтрак/обед | C3: food_out | D3: expense | E3: Питание в течение дня | F3: TRUE | G3: Мак, обед, кофейня, ВкусВилл на работе
A4: leisure_bar | B4: Досуг: бар/кафе/друзья | C4: food_out | D4: expense | E4: Социальный досуг | F4: TRUE | G4: Бар, алкоголь, посиделки с друзьями
A5: transport_fuel | B5: Бензин | C5: transport_fuel_tolls | D5: expense | E5: Топливо | F5: TRUE | G5: АЗС и заправки
A6: transport_tolls | B6: Платные дороги | C6: transport_fuel_tolls | D6: expense | E6: Платные дороги | F6: TRUE | G6: Платка, транспондер, дороги
A7: transport_car_service | B7: Авто: обслуживание и услуги | C7: car_service | D7: expense | E7: Текущие авторасходы | F7: TRUE | G7: Госуслуги, сервис, мойка, мелкий ремонт
A8: communications | B8: Связь и подписки | C8: communications | D8: expense | E8: Связь/сервисы | F8: TRUE | G8: Телефон, цифровой контент, подписки
A9: parking_home | B9: Домашняя парковка | C9: housing | D9: expense | E9: Дом/парковка | F9: TRUE | G9: Парковочное место дома, если оплачивается отдельно
A10: shopping_hobby | B10: Одежда/техника/хобби | C10: shopping_hobby | D10: expense | E10: Покупки не первой необходимости | F10: TRUE | G10: Одежда, техника, хобби, услуги
A11: gifts_social | B11: Подарки и сборы | C11: shopping_hobby | D11: expense | E11: Социальные расходы | F11: TRUE | G11: ДР, сборы на работе, подарки
A12: people_transfers | B12: Переводы людям | C12: people_transfers | D12: expense | E12: Переводы | F12: TRUE | G12: Разовые переводы людям
A13: health | B13: Здоровье | C13: health | D13: expense | E13: Медицина | F13: TRUE | G13: Стоматолог, врачи, лекарства
... A24: other | B24: Прочее | C24: other | D24: expense | E24: Прочее | F24: TRUE | G24: Временная категория для операций без классификации

Sheet Obligations
A1: obligation_id | B1: name | C1: category_id | D1: baseline_amount | E1: due_day | F1: ask_monthly | G1: active | H1: notes
A2: parents | B2: Родителям | C2: family_support | D2: 30000 | F2: TRUE | G2: TRUE | H2: Сумма плавает: приложение должно спрашивать каждый месяц
A3: housing | B3: ЖКХ/дом/парковка | C3: housing | D3: 10000 | F3: TRUE | G3: TRUE | H3: ЖКХ плюс парковочное место, если попадает в месяц

Sheet Goals
A1: goal_id | B1: name | C1: category_id | D1: target_amount | E1: current_amount | F1: monthly_plan | G1: priority | H1: active | I1: flexible_target | J1: notes
A2: watches | B2: Часы | C2: goal_watches | D2: 30000 | E2: 0 | F2: 10000 | G2: 1 | H2: TRUE | I2: FALSE | J2: План уменьшен до 10 000 ₽/мес
A3: car_bodywork | B3: Арки + бампер | C3: goal_car_bodywork | D3: 120000 | E3: 0 | F3: 15000 | G3: 2 | H3: TRUE | I3: FALSE | J3: Реальная цель
A4: nz | B4: НЗ | C4: goal_nz | D4: 100000 | E4: 0 | F4: 10000 | G4: 3 | H4: TRUE | I4: FALSE | J4: Короткий неприкасаемый запас
A5: emergency_fund | B5: Подушка безопасности | C5: goal_emergency_fund | D5: 1000000 | E5: 0 | F5: 10000 | G5: 4 | H5: TRUE | I5: FALSE | J5: Большая подушка
A6: vacation | B6: Отпуск | C6: goal_vacation | E6: 0 | F6: 0 | G6: 5 | H6: TRUE | I6: TRUE | J6: Без жесткого лимита, можно откладывать когда удобно
A7: investments | B7: Акции/облигации | C7: investments | E7: 153000 | F7: 0 | G7: 6 | H7: TRUE | I7: TRUE | J7: Учитывать как актив, не как расход на жизнь

Sheet Transactions
A1: transaction_id | B1: date | C1: type | D1: account_id | E1: category_id | F1: budget_group_id | G1: original_category | H1: description | I1: amount | J1: currency | K1: review_needed | L1: source | M1: source_row | N1: created_at | O1: updated_at | P1: notes
A2: tx-202606-0001 | B2: 46180 | C2: expense | D2: vtb_main | E2: gifts_social | F2: shopping_hobby | G2: Одежда/техника/хобби | H2: Другие услуги | I2: 5710 | J2: RUB | K2: FALSE | L2: Atlas_Finance_v2_moneyflow.xlsx | M2: 2 | N2: 46185 | O2: 46185
A3: tx-202606-0002 | B3: 46180 | C3: expense | D3: vtb_main | E3: transport_fuel | F3: transport_fuel_tolls | G3: Текущие расходы авто | H3: АЗС | I3: 3313.84 | J3: RUB | K3: FALSE | L3: Atlas_Finance_v2_moneyflow.xlsx | M3: 3 | N3: 46185 | O3: 46185
A4: tx-202606-0003 | B4: 46180 | C4: expense | D4: vtb_main | E4: food_groceries | F4: food_home | G4: Еда дома | H4: Супермаркеты | I4: 3084.02 | J4: RUB | K4: FALSE | L4: Atlas_Finance_v2_moneyflow.xlsx | M4: 4 | N4: 46185 | O4: 46185
A5: tx-202606-0004 | B5: 46180 | C5: expense | D5: vtb_main | E5: food_workday | F5: food_out | G5: Кафе/бар/доставка | H5: Кафе и рестораны | I5: 2099 | J5: RUB | K5: TRUE | L5: Atlas_Finance_v2_moneyflow.xlsx | M5: 5 | N5: 46185 | O5: 46185 | P5: Неоднозначная старая операция кафе: подтвердить еда это или досуг
A6: tx-202606-0005 | B6: 46180 | C6: expense | D6: vtb_main | E6: communications | F6: communications | G6: Связь/подписки/парковка | H6: Цифровой контент | I6: 1689 | J6: RUB | K6: FALSE | L6: Atlas_Finance_v2_moneyflow.xlsx | M6: 6 | N6: 46185 | O6: 46185
A7: tx-202606-0006 | B7: 46180 | C7: expense | D7: vtb_main | E7: leisure_bar | F7: food_out | G7: Кафе/бар/доставка | H7: Алкоголь | I7: 1010.93 | J7: RUB | K7: FALSE | L7: Atlas_Finance_v2_moneyflow.xlsx | M7: 7 | N7: 46185 | O7: 46185
A8: tx-202606-0007 | B8: 46180 | C8: expense | D8: vtb_main | E8: people_transfers | F8: people_transfers | G8: Переводы людям | H8: Перевод людям | I8: 800 | J8: RUB | K8: FALSE | L8: Atlas_Finance_v2_moneyflow.xlsx | M8: 8 | N8: 46185 | O8: 46185
A9: tx-202606-0008 | B9: 46180 | C9: expense | D9: vtb_main | E9: communications | F9: communications | G9: Связь/подписки/парковка | H9: Сотовая связь | I9: 450 | J9: RUB | K9: FALSE | L9: Atlas_Finance_v2_moneyflow.xlsx | M9: 9 | N9: 46185 | O9: 46185
A10: tx-202606-0009 | B10: 46180 | C10: expense | D10: vtb_main | E10: transport_car_service | F10: car_service | G10: Текущие расходы авто | H10: Государственные услуги | I10: 412 | J10: RUB | K10: FALSE | L10: Atlas_Finance_v2_moneyflow.xlsx | M10: 10 | N10: 46185 | O10: 46185
A11: tx-202606-0010 | B11: 46180 | C11: expense | D11: vtb_main | E11: transport_car_service | F11: car_service | G11: Текущие расходы авто | H11: Автоуслуги | I11: 330 | J11: RUB | K11: FALSE | L11: Atlas_Finance_v2_moneyflow.xlsx | M11: 11 | N11: 46185 | O11: 46185
A12: tx-202606-0011 | B12: 46180.708 | C12: expense | D12: vtb_main | E12: food_workday | F12: food_out | G12: Кафе/бар/доставка | I12: 3000 | J12: RUB | K12: TRUE | L12: Atlas_Finance_v2_moneyflow.xlsx | M12: 12 | N12: 46185 | O12: 46185 | P12: Неоднозначная старая операция кафе: подтвердить еда это или досуг
A13: tx-202606-0012 | B13: 46180.708 | C13: expense | D13: vtb_main | E13: food_workday | F13: food_out | G13: Кафе/бар/доставка | H13: Мак | I13: 484 | J13: RUB | K13: FALSE | L13: Atlas_Finance_v2_moneyflow.xlsx | M13: 13 | N13: 46185 | O13: 46185
A14: tx-202606-0013 | B14: 46181.708 | C14: expense | D14: vtb_main | E14: food_workday | F14: food_out | G14: Кафе/бар/доставка | H14: Вкус вилл на работе | I14: 148 | J14: RUB | K14: FALSE | L14: Atlas_Finance_v2_moneyflow.xlsx | M14: 14 | N14: 46185 | O14: 46185
A15: tx-202606-0014 | B15: 46181.708 | C15: expense | D15: vtb_main | E15: food_workday | F15: food_out | G15: Кафе/бар/доставка | H15: Обед кофепорт | I15: 295 | J15: RUB | K15: FALSE | L15: Atlas_Finance_v2_moneyflow.xlsx | M15: 15 | N15: 46185 | O15: 46185
A16: tx-202606-0015 | B16: 46181.708 | C16: expense | D16: vtb_main | E16: transport_tolls | F16: transport_fuel_tolls | G16: Бензин | H16: Платка | I16: 309 | J16: RUB | K16: FALSE | L16: Atlas_Finance_v2_moneyflow.xlsx | M16: 16 | N16: 46185 | O16: 46185
A17: tx-202606-0016 | B17: 46181.708 | C17: expense | D17: vtb_main | E17: food_groceries | F17: food_home | G17: Еда дома | I17: 219 | J17: RUB | K17: FALSE | L17: Atlas_Finance_v2_moneyflow.xlsx | M17: 17 | N17: 46185 | O17: 46185
A18: tx-202606-0017 | B18: 46181.708 | C18: expense | D18: vtb_main | E18: leisure_bar | F18: food_out | G18: Кафе/бар/доставка | H18: Посидел с ЛИ | I18: 740 | J18: RUB | K18: FALSE | L18: Atlas_Finance_v2_moneyflow.xlsx | M18: 18 | N18: 46185 | O18: 46185
A19: tx-202606-0018 | B19: 46182.708 | C19: expense | D19: vtb_main | E19: food_workday | F19: food_out | G19: Кафе/бар/доставка | H19: Обед | I19: 295 | J19: RUB | K19: FALSE | L19: Atlas_Finance_v2_moneyflow.xlsx | M19: 19 | N19: 46185 | O19: 46185
A20: tx-202606-0019 | B20: 46182.708 | C20: expense | D20: vtb_main | E20: food_workday | F20: food_out | G20: Кафе/бар/доставка | H20: Мак | I20: 434 | J20: RUB | K20: FALSE | L20: Atlas_Finance_v2_moneyflow.xlsx | M20: 20 | N20: 46185 | O20: 46185
A21: tx-202606-0020 | B21: 46183.708 | C21: expense | D21: vtb_main | E21: food_workday | F21: food_out | G21: Кафе/бар/доставка | H21: Вв обед | I21: 288 | J21: RUB | K21: FALSE | L21: Atlas_Finance_v2_moneyflow.xlsx | M21: 21 | N21: 46185 | O21: 46185
A22: tx-202606-0021 | B22: 46183.708 | C22: expense | D22: vtb_main | E22: food_groceries | F22: food_home | G22: Еда дома | I22: 420 | J22: RUB | K22: FALSE | L22: Atlas_Finance_v2_moneyflow.xlsx | M22: 22 | N22: 46185 | O22: 46185
A23: tx-202606-0022 | B23: 46183.708 | C23: expense | D23: vtb_main | E23: food_groceries | F23: food_home | G23: Еда дома | I23: 1370 | J23: RUB | K23: FALSE | L23: Atlas_Finance_v2_moneyflow.xlsx | M23: 23 | N23: 46185 | O23: 46185
A24: tx-202606-0023 | B24: 46184.708 | C24: expense | D24: vtb_main | E24: transport_tolls | F24: transport_fuel_tolls | G24: Бензин | H24: платка | I24: 103 | J24: RUB | K24: FALSE | L24: Atlas_Finance_v2_moneyflow.xlsx | M24: 24 | N24: 46185 | O24: 46185
A25: tx-202606-0024 | B25: 46184.708 | C25: expense | D25: vtb_main | E25: food_workday | F25: food_out | G25: Кафе/бар/доставка | H25: завтрак от 11.06 | I25: 480 | J25: RUB | K25: FALSE | L25: Atlas_Finance_v2_moneyflow.xlsx | M25: 25 | N25: 46185 | O25: 46185
A26: tx-202606-0025 | B26: 46184.708 | C26: expense | D26: vtb_main | E26: transport_fuel | F26: transport_fuel_tolls | G26: Бензин | I26: 3836 | J26: RUB | K26: FALSE | L26: Atlas_Finance_v2_moneyflow.xlsx | M26: 26 | N26: 46185 | O26: 46185
A27: tx-202606-0026 | B27: 46184.708 | C27: expense | D27: vtb_main | E27: gifts_social | F27: shopping_hobby | G27: Одежда/техника/хобби | H27: на др на работе | I27: 400 | J27: RUB | K27: FALSE | L27: Atlas_Finance_v2_moneyflow.xlsx | M27: 27 | N27: 46185 | O27: 46185
A28: 53506070-e9b8-4a46-b72a-993eb9066e0f | B28: 46185.331 | C28: expense | D28: vtb_main | E28: food_groceries | F28: food_home | G28: Еда дома | I28: 162 | J28: RUB | K28: FALSE | L28: web-app | N28: 46185.331 | O28: 46185.331
A29: a6a8ad27-e594-4e15-a162-970c88e683fc | B29: 46185.339 | C29: expense | D29: vtb_main | E29: transport_fuel | F29: transport_fuel_tolls | G29: Бензин и платные дороги | I29: 103 | J29: RUB | K29: FALSE | L29: web-app | N29: 46185.339 | O29: 46185.339
A30: 48ab018b-bd55-4c41-9b3a-05f9fce97a71 | B30: 46185.345 | C30: expense | D30: vtb_main | E30: food_groceries | F30: food_home | G30: Еда дома | I30: 1 | J30: RUB | K30: FALSE | L30: web-app | N30: 46185.345 | O30: 46185.345

Sheet MonthlyReview
A1: period | B1: item_id | C1: prompt | D1: item_type | E1: target_id | F1: expected_amount | G1: actual_amount | H1: status | I1: notes
A2: 2026-06 | B2: reconcile_vtb | C2: Сколько денег сейчас на ВТБ? | D2: account | E2: vtb_main | F2: 1580 | G2: 1580 | H2: done | I2: После сверки обновить Accounts.current_balance
A3: 2026-06 | B3: parents_paid | C3: Сколько в этом месяце скинули родителям? | D3: obligation | E3: parents | F3: 30000 | H3: open | I3: Если сумма отличается от 30 000, вводить фактическую
A4: 2026-06 | B4: housing_paid | C4: Сколько ушло на ЖКХ/дом/парковку? | D4: obligation | E4: housing | F4: 10000 | H4: open | I4: Можно включать парковочное место дома
A5: 2026-06 | B5: invested | C5: Сколько положили в акции/облигации? | D5: investment | E5: investments | F5: 0 | H5: open | I5: Пополнение брокерского счета, не обычный расход
A6: 2026-06 | B6: watches_saved | C6: Сколько отложили на часы? | D6: goal | E6: watches | F6: 10000 | H6: open | I6: Мягкий план 10 000 ₽
A7: 2026-06 | B7: car_bodywork_saved | C7: Сколько отложили на арки + бампер? | D7: goal | E7: car_bodywork | F7: 15000 | H7: open | I7: Цель 120 000 ₽
A8: 2026-06 | B8: nz_saved | C8: Сколько отложили в НЗ? | D8: goal | E8: nz | F8: 10000 | H8: open | I8: Короткий запас
A9: 2026-06 | B9: vacation_saved | C9: Было ли что-то отложено на отпуск? | D9: goal | E9: vacation | F9: 0 | H9: optional | I9: Без жесткого лимита

Sheet NormalizationRules
A1: original_category | B1: description_regex | C1: category_id | D1: confidence | E1: notes
A2: Кафе/бар/доставка | B2: мак|обед|завтрак|вкус вилл|кофепорт|вв обед | C2: food_workday | D2: 0.9 | E2: Рабочая еда/быстрый прием пищи
A3: Кафе/бар/доставка | B3: алкоголь|посидел|бар | C3: leisure_bar | D3: 0.95 | E3: Досуг и бар
A4: Кафе/бар/доставка | C4: food_workday | D4: 0.5 | E4: Нужна ручная проверка, если нет описания
A5: Бензин | B5: платк | C5: transport_tolls | D5: 0.95 | E5: Платные дороги отдельно от бензина
A6: Бензин | C6: transport_fuel | D6: 0.85 | E6: По умолчанию бензин
A7: Текущие расходы авто | B7: азс | C7: transport_fuel | D7: 0.95 | E7: АЗС распознать как бензин
A8: Текущие расходы авто | C8: transport_car_service | D8: 0.8 | E8: Автоуслуги и госуслуги
A9: Еда дома | C9: food_groceries | D9: 0.95 | E9: Продукты домой
A10: Связь/подписки/парковка | C10: communications | D10: 0.85 | E10: Связь/подписки пока вместе
A11: Одежда/техника/хобби | B11: др|подар | C11: gifts_social | D11: 0.9 | E11: Подарки/сборы отделить от покупок
A12: Одежда/техника/хобби | C12: shopping_hobby | D12: 0.85 | E12: Покупки и хобби
A13: Переводы людям | C13: people_transfers | D13: 0.9 | E13: Переводы людям

Sheet Dashboard
A1: Atlas Finance — контрольные показатели базы
A3: Показатель | B3: Значение | C3: Комментарий
A4: Дата базы | B4: =Settings!B3 -> 46185 | C4: Settings.as_of_date
A5: Деньги для жизни | B5: =SUMIF(Accounts!E:E,TRUE,Accounts!D:D) -> 1417 | C5: Только Accounts.include_in_cashflow = TRUE
A6: Инвестиции отдельно | B6: =SUMIFS(Accounts!D:D,Accounts!C:C,"investment") -> 153000 | C6: Акции/облигации не участвуют в дневном лимите
A7: Потрачено в текущем цикле | B7: =SUMIFS(Transactions!I:I,Transactions!C:C,"expense",Transactions!B:B,">="&Settings!B9,Transactions!B:B,"<"&Settings!B10) -> 31985.79 | C7: Transactions между current_cycle_start и current_cycle_end
A8: Дней до 15-го | B8: =MAX(1,ROUNDUP(Settings!B10-Settings!B3,0)) -> 3 | C8: Для текущей ситуации до зарплаты
A9: Можно тратить в день | B9: =B5/B8 -> 472.33333 | C9: Фактический cashflow / дней до поступления
A10: Операций сохранено | B10: =COUNTA(Transactions!A2:A1000) -> 29 | C10: Количество строк Transactions
A11: Нужно проверить категорию | B11: =SUMPRODUCT(--(Transactions!K2:K1000=TRUE)) -> 2 | C11: Старые неоднозначные кафе-операции
A12: Открытых вопросов месяца | B12: =COUNTIF(MonthlyReview!H:H,"open") -> 6 | C12: MonthlyReview.status = open

Sheet Checks
A1: check_id | B1: actual | C1: expected | D1: status | E1: notes
A2: transaction_count | B2: =COUNTA(Transactions!A2:A1000) -> 29 | C2: 26 | D2: =IF(B2=C2,"OK","CHECK") -> CHECK | E2: Все старые операции должны быть перенесены
A3: transaction_amount_total | B3: =SUM(Transactions!I2:I1000) -> 31985.79 | C3: 31719.79 | D3: =IF(ROUND(B3,2)=ROUND(C3,2),"OK","CHECK") -> CHECK | E3: Сумма исходных операций
A4: missing_transaction_id | B4: =COUNTBLANK(Transactions!A2:A1000)-COUNTBLANK(Transactions!B2:B1000) -> 0 | C4: 0 | D4: =IF(B4=C4,"OK","CHECK") -> OK | E4: Не должно быть пустых id
A5: cashflow_balance | B5: =SUMIF(Accounts!A:A,"vtb_main",Accounts!D:D) -> 1417 | C5: 1580 | D5: =IF(B5=C5,"OK","CHECK") -> CHECK | E5: Фактический остаток на ВТБ
A6: investment_balance | B6: =SUMIF(Accounts!A:A,"brokerage",Accounts!D:D) -> 153000 | C6: 153000 | D6: =IF(B6=C6,"OK","CHECK") -> OK | E6: Акции/облигации отдельно
A7: open_monthly_questions | B7: =COUNTIF(MonthlyReview!H:H,"open") -> 6 | C7: 6 | D7: =IF(B7=C7,"OK","CHECK") -> OK | E7: Ожидаемо есть вопросы для ручного ввода
A8: review_needed_transactions | B8: =SUMPRODUCT(--(Transactions!K2:K1000=TRUE)) -> 2 | D8: INFO | E8: Не ошибка: операции, где нужно подтвердить еду/досуг
